viqubox_sdk/__init__.py
viqubox_sdk/_main.py
viqubox_sdk/_util.py
viqubox_sdk/client.py
viqubox_sdk/exceptions.py
viqubox_sdk/models.py
viqubox_sdk-0.4.6.dist-info/METADATA
viqubox_sdk-0.4.6.dist-info/WHEEL
viqubox_sdk-0.4.6.dist-info/RECORD
