Metadata-Version: 2.1
Name: viqubox-sdk
Version: 0.4.6
Summary: ViQuBox SDK - Create and send processing requests to the ViQuBox system.
Author: Gvido Bērziņš
Author-email: gvido.berzins@testdevlab.com
Requires-Python: >=3.8,<4.0
Classifier: Programming Language :: Python :: 3
Classifier: Programming Language :: Python :: 3.8
Classifier: Programming Language :: Python :: 3.9
Classifier: Programming Language :: Python :: 3.10
Classifier: Programming Language :: Python :: 3.11
Requires-Dist: attrs (>=22.1.0,<23.0.0)
Requires-Dist: attrs-strict (>=1.0.0,<2.0.0)
Requires-Dist: cattrs (>=22.1.0,<23.0.0)
Requires-Dist: requests (>=2.28.1,<3.0.0)
Requires-Dist: typeguard (>=2.13.3,<3.0.0)
